{"kind":"identitytoolkit#DownloadAccountResponse","users":[{"localId":"7SYKFKS94UiknYQMcC5W371owG48","createdAt":"1694701441474","lastLoginAt":"1694701441474","passwordHash":"fakeHash:salt=fakeSalt9ZLlgDyhk0D6s79Mxagk:password=A93gc8uSWwA6","salt":"fakeSalt9ZLlgDyhk0D6s79Mxagk","passwordUpdatedAt":1694706466283,"providerUserInfo":[{"providerId":"password","email":"testuser4@example.com","federatedId":"testuser4@example.com","rawId":"testuser4@example.com"}],"validSince":"1694706466","email":"testuser4@example.com","emailVerified":false,"disabled":false},{"localId":"FAo4AdiB0zGiC0eaZkwBMWWipnCW","createdAt":"1694701441531","lastLoginAt":"1694701441531","passwordHash":"fakeHash:salt=fakeSalt2Yqa5xY6Q0d40DxXdduF:password=bc79icDPmxef","salt":"fakeSalt2Yqa5xY6Q0d40DxXdduF","passwordUpdatedAt":1694706466284,"providerUserInfo":[{"providerId":"password","email":"testuser8@example.com","federatedId":"testuser8@example.com","rawId":"testuser8@example.com"}],"validSince":"1694706466","email":"testuser8@example.com","emailVerified":false,"disabled":false},{"localId":"KWtNwDodPY2vWhp1MAssSwWPTmGQ","createdAt":"1694701441402","lastLoginAt":"1694701441402","passwordHash":"fakeHash:salt=fakeSaltGL5XnjzQBQnJgW723sMq:password=Vd0ohXr29U25","salt":"fakeSaltGL5XnjzQBQnJgW723sMq","passwordUpdatedAt":1694706466284,"providerUserInfo":[{"providerId":"password","email":"testuser1@example.com","federatedId":"testuser1@example.com","rawId":"testuser1@example.com"}],"validSince":"1694706466","email":"testuser1@example.com","emailVerified":false,"disabled":false},{"localId":"WWQ56Ntpqh3wlwDxxIERKVdPIO6D","createdAt":"1694701441459","lastLoginAt":"1694701441459","passwordHash":"fakeHash:salt=fakeSalt8ssXvvxCHKb2tRfE0NRS:password=WDdWVXcc0wPm","salt":"fakeSalt8ssXvvxCHKb2tRfE0NRS","passwordUpdatedAt":1694706466284,"providerUserInfo":[{"providerId":"password","email":"testuser3@example.com","federatedId":"testuser3@example.com","rawId":"testuser3@example.com"}],"validSince":"1694706466","email":"testuser3@example.com","emailVerified":false,"disabled":false},{"localId":"f9yzKhZO2f30DmfPm3dAyPw7klt7","createdAt":"1694701441505","lastLoginAt":"1694701441505","passwordHash":"fakeHash:salt=fakeSaltqTZdTExpl2DtNvi5choL:password=j26j7IvVhqOO","salt":"fakeSaltqTZdTExpl2DtNvi5choL","passwordUpdatedAt":1694706466284,"providerUserInfo":[{"providerId":"password","email":"testuser6@example.com","federatedId":"testuser6@example.com","rawId":"testuser6@example.com"}],"validSince":"1694706466","email":"testuser6@example.com","emailVerified":false,"disabled":false},{"localId":"munceYxWmtr7xwSEd3pQMgnUuei7","createdAt":"1694701441441","lastLoginAt":"1694701441441","passwordHash":"fakeHash:salt=fakeSaltM2bEGbNmciuRet7sfk0w:password=zkKi5011tCFu","salt":"fakeSaltM2bEGbNmciuRet7sfk0w","passwordUpdatedAt":1694706466285,"providerUserInfo":[{"providerId":"password","email":"testuser2@example.com","federatedId":"testuser2@example.com","rawId":"testuser2@example.com"}],"validSince":"1694706466","email":"testuser2@example.com","emailVerified":false,"disabled":false},{"localId":"oxnBOexZdACY8NclbPaoh3UVur34","createdAt":"1694701441544","lastLoginAt":"1694701441544","passwordHash":"fakeHash:salt=fakeSaltd4RZvWA0ccsVekhLhi97:password=YGYw53hIhJGs","salt":"fakeSaltd4RZvWA0ccsVekhLhi97","passwordUpdatedAt":1694706466285,"providerUserInfo":[{"providerId":"password","email":"testuser9@example.com","federatedId":"testuser9@example.com","rawId":"testuser9@example.com"}],"validSince":"1694706466","email":"testuser9@example.com","emailVerified":false,"disabled":false},{"localId":"xyz8mhwzw0MlUaXqvR6tJN6Ezt3j","createdAt":"1694701441489","lastLoginAt":"1694701441489","passwordHash":"fakeHash:salt=fakeSaltnv5mgu7JZ06zDhujNRxT:password=QSguE7CXzb3d","salt":"fakeSaltnv5mgu7JZ06zDhujNRxT","passwordUpdatedAt":1694706466285,"providerUserInfo":[{"providerId":"password","email":"testuser5@example.com","federatedId":"testuser5@example.com","rawId":"testuser5@example.com"}],"validSince":"1694706466","email":"testuser5@example.com","emailVerified":false,"disabled":false},{"localId":"yoaF2LSDI6lb1gxPGmlFWDEHxair","createdAt":"1694701441518","lastLoginAt":"1694701441518","passwordHash":"fakeHash:salt=fakeSaltvmqc6XK7z4BoB0XsFijt:password=PGlU2xSZAeu6","salt":"fakeSaltvmqc6XK7z4BoB0XsFijt","passwordUpdatedAt":1694706466285,"providerUserInfo":[{"providerId":"password","email":"testuser7@example.com","federatedId":"testuser7@example.com","rawId":"testuser7@example.com"}],"validSince":"1694706466","email":"testuser7@example.com","emailVerified":false,"disabled":false},{"localId":"zecBTYcdGEbdl6jwcVwLvtnwnWS7","createdAt":"1694701441556","lastLoginAt":"1694701441556","passwordHash":"fakeHash:salt=fakeSalt3XiFgyb2r8RE5NzHXhsl:password=0xcOJy3JPICp","salt":"fakeSalt3XiFgyb2r8RE5NzHXhsl","passwordUpdatedAt":1694706466285,"providerUserInfo":[{"providerId":"password","email":"testuser10@example.com","federatedId":"testuser10@example.com","rawId":"testuser10@example.com"}],"validSince":"1694706466","email":"testuser10@example.com","emailVerified":false,"disabled":false}]}